AUTHORS
MANIFEST.in
README.md
setup.py
src/pmap/__init__.py
src/pmap/core.py
src/python_pmap.egg-info/PKG-INFO
src/python_pmap.egg-info/SOURCES.txt
src/python_pmap.egg-info/dependency_links.txt
src/python_pmap.egg-info/not-zip-safe
src/python_pmap.egg-info/requires.txt
src/python_pmap.egg-info/top_level.txt