Metadata-Version: 1.1
Name: python-pmap
Version: 2.0.0
Summary: Clojure's pmap implementation for Python.
Home-page: https://github.com/hcarvalhoalves/python-pmap
Author: Henrique Carvalho Alves
Author-email: hcarvalhoalves@gmail.com
License: UNKNOWN
Platform: UNKNOWN
Classifier: Programming Language :: Python :: 2.7
Classifier: Programming Language :: Python :: 3.6
